plausible/__init__.py
plausible/py.typed
plausible/utils.py
plausible/contrib/__init__.py
plausible/contrib/wagtail/__init__.py
plausible/contrib/wagtail/apps.py
plausible/contrib/wagtail/models.py
plausible/contrib/wagtail/validators.py
plausible/contrib/wagtail/migrations/0001_initial.py
plausible/contrib/wagtail/migrations/__init__.py
plausible/contrib/wagtail/templatetags/__init__.py
plausible/contrib/wagtail/templatetags/plausible_wagtail.py
plausible/templatetags/__init__.py
plausible/templatetags/plausible.py
django_plausible-0.5.0.dist-info/LICENSE
django_plausible-0.5.0.dist-info/METADATA
django_plausible-0.5.0.dist-info/WHEEL
django_plausible-0.5.0.dist-info/top_level.txt
django_plausible-0.5.0.dist-info/RECORD
