Metadata-Version: 2.1
Name: django-plausible
Version: 0.5.0
Summary:  Django module to provide easy Plausible integration, with Wagtail support
Home-page: https://github.com/RealOrangeOne/django-plausible
Author: Jake Howard
License: BSD
Keywords: django plausible wagtail analytics
Classifier: Environment :: Web Environment
Classifier: Framework :: Wagtail
Classifier: Framework :: Wagtail :: 4
Classifier: Framework :: Wagtail :: 5
Classifier: Framework :: Django
Classifier: Framework :: Django :: 3.2
Classifier: Framework :: Django :: 4.0
Classifier: Framework :: Django :: 4.1
Classifier: Framework :: Django :: 4.2
Classifier: Intended Audience :: Developers
Classifier: License :: OSI Approved :: BSD License
Classifier: Operating System :: OS Independent
Classifier: Programming Language :: Python :: 3.7
Classifier: Programming Language :: Python :: 3.8
Classifier: Programming Language :: Python :: 3.9
Classifier: Programming Language :: Python :: 3.10
Classifier: Programming Language :: Python :: 3.11
Classifier: Programming Language :: Python :: 3
Classifier: Programming Language :: Python
Classifier: Topic :: Internet :: WWW/HTTP
Classifier: Topic :: Software Development
Classifier: Typing :: Typed
Requires-Python: >=3.7
Provides-Extra: wagtail
License-File: LICENSE
